{
  "id": "ec7da562-7e21-4dac-a0d2-f4441e1efd3b",
  "revision": 0,
  "last_node_id": 115,
  "last_link_id": 213,
  "nodes": [
    {
      "id": 75,
      "type": "UNETLoader",
      "pos": [
        -260,
        1800
      ],
      "size": [
        430,
        82
      ],
      "flags": {},
      "order": 0,
      "mode": 0,
      "inputs": [],
      "outputs": [
        {
          "name": "MODEL",
          "type": "MODEL",
          "slot_index": 0,
          "links": [
            173
          ]
        }
      ],
      "properties": {
        "Node name for S&R": "UNETLoader",
        "cnr_id": "comfy-core",
        "ver": "0.3.50",
        "models": [
          {
            "name": "wan2.2_fun_camera_high_noise_14B_fp8_scaled.safetensors",
            "url": "https://huggingface.co/Comfy-Org/Wan_2.2_ComfyUI_Repackaged/resolve/main/split_files/diffusion_models/wan2.2_fun_camera_high_noise_14B_fp8_scaled.safetensors",
            "directory": "diffusion_models"
          }
        ],
        "enableTabs": false,
        "tabWidth": 65,
        "tabXOffset": 10,
        "hasSecondTab": false,
        "secondTabText": "Send Back",
        "secondTabOffset": 80,
        "secondTabWidth": 65,
        "ue_properties": {
          "widget_ue_connectable": {}
        }
      },
      "widgets_values": [
        "wan2.2_fun_camera_high_noise_14B_fp8_scaled.safetensors",
        "default"
      ]
    },
    {
      "id": 90,
      "type": "LoraLoaderModelOnly",
      "pos": [
        -250,
        2250
      ],
      "size": [
        420,
        82
      ],
      "flags": {},
      "order": 10,
      "mode": 0,
      "inputs": [
        {
          "name": "model",
          "type": "MODEL",
          "link": 177
        }
      ],
      "outputs": [
        {
          "name": "MODEL",
          "type": "MODEL",
          "links": [
            176
          ]
        }
      ],
      "properties": {
        "Node name for S&R": "LoraLoaderModelOnly",
        "cnr_id": "comfy-core",
        "ver": "0.3.50",
        "models": [
          {
            "name": "wan2.2_i2v_lightx2v_4steps_lora_v1_low_noise.safetensors",
            "url": "https://huggingface.co/Comfy-Org/Wan_2.2_ComfyUI_Repackaged/resolve/main/split_files/loras/wan2.2_i2v_lightx2v_4steps_lora_v1_low_noise.safetensors",
            "directory": "loras"
          }
        ],
        "enableTabs": false,
        "tabWidth": 65,
        "tabXOffset": 10,
        "hasSecondTab": false,
        "secondTabText": "Send Back",
        "secondTabOffset": 80,
        "secondTabWidth": 65,
        "ue_properties": {
          "widget_ue_connectable": {
            "lora_name": true,
            "strength_model": true
          }
        }
      },
      "widgets_values": [
        "wan2.2_i2v_lightx2v_4steps_lora_v1_low_noise.safetensors",
        1
      ]
    },
    {
      "id": 88,
      "type": "LoraLoaderModelOnly",
      "pos": [
        -260,
        1930
      ],
      "size": [
        430,
        82
      ],
      "flags": {},
      "order": 9,
      "mode": 0,
      "inputs": [
        {
          "name": "model",
          "type": "MODEL",
          "link": 173
        }
      ],
      "outputs": [
        {
          "name": "MODEL",
          "type": "MODEL",
          "links": [
            174
          ]
        }
      ],
      "properties": {
        "Node name for S&R": "LoraLoaderModelOnly",
        "cnr_id": "comfy-core",
        "ver": "0.3.50",
        "models": [
          {
            "name": "wan2.2_i2v_lightx2v_4steps_lora_v1_high_noise.safetensors",
            "url": "https://huggingface.co/Comfy-Org/Wan_2.2_ComfyUI_Repackaged/resolve/main/split_files/loras/wan2.2_i2v_lightx2v_4steps_lora_v1_high_noise.safetensors",
            "directory": "loras"
          }
        ],
        "enableTabs": false,
        "tabWidth": 65,
        "tabXOffset": 10,
        "hasSecondTab": false,
        "secondTabText": "Send Back",
        "secondTabOffset": 80,
        "secondTabWidth": 65,
        "ue_properties": {
          "widget_ue_connectable": {
            "lora_name": true,
            "strength_model": true
          }
        }
      },
      "widgets_values": [
        "wan2.2_i2v_lightx2v_4steps_lora_v1_high_noise.safetensors",
        1
      ]
    },
    {
      "id": 72,
      "type": "UNETLoader",
      "pos": [
        -260,
        2120
      ],
      "size": [
        430,
        82
      ],
      "flags": {},
      "order": 1,
      "mode": 0,
      "inputs": [],
      "outputs": [
        {
          "name": "MODEL",
          "type": "MODEL",
          "slot_index": 0,
          "links": [
            177
          ]
        }
      ],
      "properties": {
        "Node name for S&R": "UNETLoader",
        "cnr_id": "comfy-core",
        "ver": "0.3.50",
        "models": [
          {
            "name": "wan2.2_fun_camera_low_noise_14B_fp8_scaled.safetensors",
            "url": "https://huggingface.co/Comfy-Org/Wan_2.2_ComfyUI_Repackaged/resolve/main/split_files/diffusion_models/wan2.2_fun_camera_low_noise_14B_fp8_scaled.safetensors",
            "directory": "diffusion_models"
          }
        ],
        "enableTabs": false,
        "tabWidth": 65,
        "tabXOffset": 10,
        "hasSecondTab": false,
        "secondTabText": "Send Back",
        "secondTabOffset": 80,
        "secondTabWidth": 65,
        "ue_properties": {
          "widget_ue_connectable": {}
        }
      },
      "widgets_values": [
        "wan2.2_fun_camera_low_noise_14B_fp8_scaled.safetensors",
        "default"
      ]
    },
    {
      "id": 80,
      "type": "WanCameraImageToVideo",
      "pos": [
        550,
        2830
      ],
      "size": [
        290,
        230
      ],
      "flags": {},
      "order": 15,
      "mode": 0,
      "inputs": [
        {
          "name": "positive",
          "type": "CONDITIONING",
          "link": 161
        },
        {
          "name": "negative",
          "type": "CONDITIONING",
          "link": 162
        },
        {
          "name": "vae",
          "type": "VAE",
          "link": 163
        },
        {
          "name": "clip_vision_output",
          "shape": 7,
          "type": "CLIP_VISION_OUTPUT",
          "link": null
        },
        {
          "name": "start_image",
          "shape": 7,
          "type": "IMAGE",
          "link": 164
        },
        {
          "name": "camera_conditions",
          "shape": 7,
          "type": "WAN_CAMERA_EMBEDDING",
          "link": 165
        },
        {
          "name": "width",
          "type": "INT",
          "widget": {
            "name": "width"
          },
          "link": 166
        },
        {
          "name": "height",
          "type": "INT",
          "widget": {
            "name": "height"
          },
          "link": 167
        },
        {
          "name": "length",
          "type": "INT",
          "widget": {
            "name": "length"
          },
          "link": 168
        }
      ],
      "outputs": [
        {
          "name": "positive",
          "type": "CONDITIONING",
          "links": [
            150,
            158
          ]
        },
        {
          "name": "negative",
          "type": "CONDITIONING",
          "links": [
            151,
            159
          ]
        },
        {
          "name": "latent",
          "type": "LATENT",
          "links": [
            152
          ]
        }
      ],
      "properties": {
        "Node name for S&R": "WanCameraImageToVideo",
        "cnr_id": "comfy-core",
        "ver": "0.3.50",
        "enableTabs": false,
        "tabWidth": 65,
        "tabXOffset": 10,
        "hasSecondTab": false,
        "secondTabText": "Send Back",
        "secondTabOffset": 80,
        "secondTabWidth": 65,
        "ue_properties": {
          "widget_ue_connectable": {
            "width": true,
            "height": true,
            "length": true
          }
        }
      },
      "widgets_values": [
        832,
        480,
        81,
        1
      ]
    },
    {
      "id": 76,
      "type": "ModelSamplingSD3",
      "pos": [
        250,
        1750
      ],
      "size": [
        210,
        60
      ],
      "flags": {},
      "order": 13,
      "mode": 0,
      "inputs": [
        {
          "name": "model",
          "type": "MODEL",
          "link": 174
        }
      ],
      "outputs": [
        {
          "name": "MODEL",
          "type": "MODEL",
          "slot_index": 0,
          "links": [
            149
          ]
        }
      ],
      "properties": {
        "Node name for S&R": "ModelSamplingSD3",
        "cnr_id": "comfy-core",
        "ver": "0.3.50",
        "enableTabs": false,
        "tabWidth": 65,
        "tabXOffset": 10,
        "hasSecondTab": false,
        "secondTabText": "Send Back",
        "secondTabOffset": 80,
        "secondTabWidth": 65,
        "ue_properties": {
          "widget_ue_connectable": {}
        }
      },
      "widgets_values": [
        8.000000000000002
      ]
    },
    {
      "id": 77,
      "type": "ModelSamplingSD3",
      "pos": [
        270,
        1930
      ],
      "size": [
        210,
        60
      ],
      "flags": {},
      "order": 14,
      "mode": 0,
      "inputs": [
        {
          "name": "model",
          "type": "MODEL",
          "link": 176
        }
      ],
      "outputs": [
        {
          "name": "MODEL",
          "type": "MODEL",
          "slot_index": 0,
          "links": [
            157
          ]
        }
      ],
      "properties": {
        "Node name for S&R": "ModelSamplingSD3",
        "cnr_id": "comfy-core",
        "ver": "0.3.50",
        "enableTabs": false,
        "tabWidth": 65,
        "tabXOffset": 10,
        "hasSecondTab": false,
        "secondTabText": "Send Back",
        "secondTabOffset": 80,
        "secondTabWidth": 65,
        "ue_properties": {
          "widget_ue_connectable": {}
        }
      },
      "widgets_values": [
        8
      ]
    },
    {
      "id": 82,
      "type": "VAEDecode",
      "pos": [
        1040,
        3040
      ],
      "size": [
        210,
        46
      ],
      "flags": {},
      "order": 18,
      "mode": 0,
      "inputs": [
        {
          "name": "samples",
          "type": "LATENT",
          "link": 170
        },
        {
          "name": "vae",
          "type": "VAE",
          "link": 171
        }
      ],
      "outputs": [
        {
          "name": "IMAGE",
          "type": "IMAGE",
          "slot_index": 0,
          "links": [
            172
          ]
        }
      ],
      "properties": {
        "Node name for S&R": "VAEDecode",
        "cnr_id": "comfy-core",
        "ver": "0.3.50",
        "enableTabs": false,
        "tabWidth": 65,
        "tabXOffset": 10,
        "hasSecondTab": false,
        "secondTabText": "Send Back",
        "secondTabOffset": 80,
        "secondTabWidth": 65,
        "ue_properties": {
          "widget_ue_connectable": {}
        }
      },
      "widgets_values": []
    },
    {
      "id": 85,
      "type": "CLIPLoader",
      "pos": [
        -250,
        2400
      ],
      "size": [
        430,
        110
      ],
      "flags": {},
      "order": 2,
      "mode": 0,
      "inputs": [],
      "outputs": [
        {
          "name": "CLIP",
          "type": "CLIP",
          "slot_index": 0,
          "links": [
            154,
            169
          ]
        }
      ],
      "properties": {
        "Node name for S&R": "CLIPLoader",
        "cnr_id": "comfy-core",
        "ver": "0.3.50",
        "models": [
          {
            "name": "umt5_xxl_fp8_e4m3fn_scaled.safetensors",
            "url": "https://huggingface.co/Comfy-Org/Wan_2.1_ComfyUI_repackaged/resolve/main/split_files/text_encoders/umt5_xxl_fp8_e4m3fn_scaled.safetensors",
            "directory": "text_encoders"
          }
        ],
        "enableTabs": false,
        "tabWidth": 65,
        "tabXOffset": 10,
        "hasSecondTab": false,
        "secondTabText": "Send Back",
        "secondTabOffset": 80,
        "secondTabWidth": 65,
        "ue_properties": {
          "widget_ue_connectable": {}
        }
      },
      "widgets_values": [
        "umt5_xxl_fp8_e4m3fn_scaled.safetensors",
        "wan",
        "default"
      ]
    },
    {
      "id": 86,
      "type": "VAELoader",
      "pos": [
        -250,
        2550
      ],
      "size": [
        430,
        60
      ],
      "flags": {},
      "order": 3,
      "mode": 0,
      "inputs": [],
      "outputs": [
        {
          "name": "VAE",
          "type": "VAE",
          "slot_index": 0,
          "links": [
            163,
            171
          ]
        }
      ],
      "properties": {
        "Node name for S&R": "VAELoader",
        "cnr_id": "comfy-core",
        "ver": "0.3.50",
        "models": [
          {
            "name": "wan_2.1_vae.safetensors",
            "url": "https://huggingface.co/Comfy-Org/Wan_2.2_ComfyUI_Repackaged/resolve/main/split_files/vae/wan_2.1_vae.safetensors",
            "directory": "vae"
          }
        ],
        "enableTabs": false,
        "tabWidth": 65,
        "tabXOffset": 10,
        "hasSecondTab": false,
        "secondTabText": "Send Back",
        "secondTabOffset": 80,
        "secondTabWidth": 65,
        "ue_properties": {
          "widget_ue_connectable": {}
        }
      },
      "widgets_values": [
        "wan_2.1_vae.safetensors"
      ]
    },
    {
      "id": 71,
      "type": "KSamplerAdvanced",
      "pos": [
        950,
        1760
      ],
      "size": [
        304.748046875,
        546.0001220703125
      ],
      "flags": {},
      "order": 16,
      "mode": 0,
      "inputs": [
        {
          "name": "model",
          "type": "MODEL",
          "link": 149
        },
        {
          "name": "positive",
          "type": "CONDITIONING",
          "link": 150
        },
        {
          "name": "negative",
          "type": "CONDITIONING",
          "link": 151
        },
        {
          "name": "latent_image",
          "type": "LATENT",
          "link": 152
        }
      ],
      "outputs": [
        {
          "name": "LATENT",
          "type": "LATENT",
          "links": [
            160
          ]
        }
      ],
      "properties": {
        "Node name for S&R": "KSamplerAdvanced",
        "cnr_id": "comfy-core",
        "ver": "0.3.50",
        "enableTabs": false,
        "tabWidth": 65,
        "tabXOffset": 10,
        "hasSecondTab": false,
        "secondTabText": "Send Back",
        "secondTabOffset": 80,
        "secondTabWidth": 65,
        "ue_properties": {
          "widget_ue_connectable": {}
        }
      },
      "widgets_values": [
        "enable",
        316038771312063,
        "randomize",
        4,
        1,
        "euler",
        "simple",
        0,
        2,
        "enable"
      ]
    },
    {
      "id": 78,
      "type": "KSamplerAdvanced",
      "pos": [
        960,
        2430
      ],
      "size": [
        304.748046875,
        546.0001220703125
      ],
      "flags": {},
      "order": 17,
      "mode": 0,
      "inputs": [
        {
          "name": "model",
          "type": "MODEL",
          "link": 157
        },
        {
          "name": "positive",
          "type": "CONDITIONING",
          "link": 158
        },
        {
          "name": "negative",
          "type": "CONDITIONING",
          "link": 159
        },
        {
          "name": "latent_image",
          "type": "LATENT",
          "link": 160
        }
      ],
      "outputs": [
        {
          "name": "LATENT",
          "type": "LATENT",
          "links": [
            170
          ]
        }
      ],
      "properties": {
        "Node name for S&R": "KSamplerAdvanced",
        "cnr_id": "comfy-core",
        "ver": "0.3.50",
        "enableTabs": false,
        "tabWidth": 65,
        "tabXOffset": 10,
        "hasSecondTab": false,
        "secondTabText": "Send Back",
        "secondTabOffset": 80,
        "secondTabWidth": 65,
        "ue_properties": {
          "widget_ue_connectable": {}
        }
      },
      "widgets_values": [
        "disable",
        0,
        "fixed",
        4,
        1,
        "euler",
        "simple",
        2,
        4,
        "disable"
      ]
    },
    {
      "id": 112,
      "type": "MarkdownNote",
      "pos": [
        -790,
        2160
      ],
      "size": [
        480,
        150
      ],
      "flags": {},
      "order": 4,
      "mode": 0,
      "inputs": [],
      "outputs": [],
      "title": "VRAM Usage",
      "properties": {},
      "widgets_values": [
        "## GPU:RTX4090D 24GB\n\n| Model            | Size |VRAM Usage | 1st Generation | 2nd Generation |\n|---------------------|-------|-----------|---------------|-----------------|\n| fp8_scaled               |640*640| 84%               | ≈  536s              | ≈ 513s                   |\n| fp8_scaled +  4steps LoRA  | 640*640  | 89%                | ≈ 108s               | ≈ 71s                   |"
      ],
      "color": "#432",
      "bgcolor": "#653"
    },
    {
      "id": 110,
      "type": "MarkdownNote",
      "pos": [
        -790,
        1680
      ],
      "size": [
        480,
        430
      ],
      "flags": {},
      "order": 5,
      "mode": 0,
      "inputs": [],
      "outputs": [],
      "properties": {},
      "widgets_values": [
        "[Tutorial](https://docs.comfy.org/tutorials/video/wan/wan2-2-fun-camera\n) | [教程](https://docs.comfy.org/zh-CN/tutorials/video/wan/wan2-2-fun-camera\n)\n\n**Diffusion Model**\n- [wan2.2_fun_camera_high_noise_14B_fp8_scaled.safetensors](https://huggingface.co/Comfy-Org/Wan_2.2_ComfyUI_Repackaged/resolve/main/split_files/diffusion_models/wan2.2_fun_camera_high_noise_14B_fp8_scaled.safetensors)\n- [wan2.2_fun_camera_low_noise_14B_fp8_scaled.safetensors](https://huggingface.co/Comfy-Org/Wan_2.2_ComfyUI_Repackaged/resolve/main/split_files/diffusion_models/wan2.2_fun_camera_low_noise_14B_fp8_scaled.safetensors)\n\n**LoRA**\n- [wan2.2_i2v_lightx2v_4steps_lora_v1_low_noise.safetensors](https://huggingface.co/Comfy-Org/Wan_2.2_ComfyUI_Repackaged/resolve/main/split_files/loras/wan2.2_i2v_lightx2v_4steps_lora_v1_low_noise.safetensors)\n- [wan2.2_i2v_lightx2v_4steps_lora_v1_high_noise.safetensors](https://huggingface.co/Comfy-Org/Wan_2.2_ComfyUI_Repackaged/resolve/main/split_files/loras/wan2.2_i2v_lightx2v_4steps_lora_v1_high_noise.safetensors)\n\n**VAE**\n- [wan_2.1_vae.safetensors](https://huggingface.co/Comfy-Org/Wan_2.2_ComfyUI_Repackaged/resolve/main/split_files/vae/wan_2.1_vae.safetensors)\n\n**Text Encoder**   \n- [umt5_xxl_fp8_e4m3fn_scaled.safetensors](https://huggingface.co/Comfy-Org/Wan_2.1_ComfyUI_repackaged/resolve/main/split_files/text_encoders/umt5_xxl_fp8_e4m3fn_scaled.safetensors)\n\n\n```\nComfyUI/\n├───📂 models/\n│   ├───📂 diffusion_models/\n│   │   ├─── wan2.2_fun_camera_high_noise_14B_fp8_scaled.safetensors\n│   │   └─── wan2.2_fun_camera_low_noise_14B_fp8_scaled.safetensors\n│   ├───📂 loras/\n│   │   ├─── wan2.2_i2v_lightx2v_4steps_lora_v1_low_noise.safetensors\n│   │   └─── wan2.2_i2v_lightx2v_4steps_lora_v1_low_noise.safetensors\n│   ├───📂 text_encoders/\n│   │   └─── umt5_xxl_fp8_e4m3fn_scaled.safetensors \n│   └───📂 vae/\n│       └── wan_2.1_vae.safetensors\n```\n"
      ],
      "color": "#432",
      "bgcolor": "#653"
    },
    {
      "id": 74,
      "type": "CLIPTextEncode",
      "pos": [
        260,
        2410
      ],
      "size": [
        580,
        200
      ],
      "flags": {},
      "order": 11,
      "mode": 0,
      "inputs": [
        {
          "name": "clip",
          "type": "CLIP",
          "link": 154
        }
      ],
      "outputs": [
        {
          "name": "CONDITIONING",
          "type": "CONDITIONING",
          "slot_index": 0,
          "links": [
            162
          ]
        }
      ],
      "title": "CLIP Text Encode (Negative Prompt)",
      "properties": {
        "Node name for S&R": "CLIPTextEncode",
        "cnr_id": "comfy-core",
        "ver": "0.3.50",
        "enableTabs": false,
        "tabWidth": 65,
        "tabXOffset": 10,
        "hasSecondTab": false,
        "secondTabText": "Send Back",
        "secondTabOffset": 80,
        "secondTabWidth": 65,
        "ue_properties": {
          "widget_ue_connectable": {}
        }
      },
      "widgets_values": [
        "static image, no movement, oversaturated colors, overexposed, blurry details, poor quality, jpeg artifacts, ugly, deformed, extra fingers, poorly drawn hands, poorly drawn face, malformed, disfigured, mutated limbs, fused fingers, frozen frame, cluttered background, three legs, crowded background, walking backwards, abrupt cuts, jerky movement, low resolution, pixelated, grainy, washed out colors, flat lighting, amateur quality, shaky camera"
      ],
      "color": "#223",
      "bgcolor": "#335"
    },
    {
      "id": 79,
      "type": "LoadImage",
      "pos": [
        -250,
        2720
      ],
      "size": [
        430,
        490
      ],
      "flags": {},
      "order": 6,
      "mode": 0,
      "inputs": [],
      "outputs": [
        {
          "name": "IMAGE",
          "type": "IMAGE",
          "slot_index": 0,
          "links": [
            164
          ]
        },
        {
          "name": "MASK",
          "type": "MASK",
          "slot_index": 1,
          "links": null
        }
      ],
      "properties": {
        "Node name for S&R": "LoadImage",
        "cnr_id": "comfy-core",
        "ver": "0.3.50",
        "enableTabs": false,
        "tabWidth": 65,
        "tabXOffset": 10,
        "hasSecondTab": false,
        "secondTabText": "Send Back",
        "secondTabOffset": 80,
        "secondTabWidth": 65,
        "ue_properties": {
          "widget_ue_connectable": {}
        }
      },
      "widgets_values": [
        "amueblar_after.png",
        "image"
      ]
    },
    {
      "id": 83,
      "type": "CreateVideo",
      "pos": [
        980,
        3140
      ],
      "size": [
        270,
        78
      ],
      "flags": {},
      "order": 19,
      "mode": 0,
      "inputs": [
        {
          "name": "images",
          "type": "IMAGE",
          "link": 172
        },
        {
          "name": "audio",
          "shape": 7,
          "type": "AUDIO",
          "link": null
        }
      ],
      "outputs": [
        {
          "name": "VIDEO",
          "type": "VIDEO",
          "links": [
            153
          ]
        }
      ],
      "properties": {
        "Node name for S&R": "CreateVideo",
        "cnr_id": "comfy-core",
        "ver": "0.3.50",
        "enableTabs": false,
        "tabWidth": 65,
        "tabXOffset": 10,
        "hasSecondTab": false,
        "secondTabText": "Send Back",
        "secondTabOffset": 80,
        "secondTabWidth": 65,
        "ue_properties": {
          "widget_ue_connectable": {
            "fps": true
          }
        }
      },
      "widgets_values": [
        30
      ]
    },
    {
      "id": 87,
      "type": "WanCameraEmbedding",
      "pos": [
        260,
        2830
      ],
      "size": [
        236.8000030517578,
        310
      ],
      "flags": {},
      "order": 7,
      "mode": 0,
      "inputs": [],
      "outputs": [
        {
          "name": "camera_embedding",
          "type": "WAN_CAMERA_EMBEDDING",
          "links": [
            165
          ]
        },
        {
          "name": "width",
          "type": "INT",
          "links": [
            166
          ]
        },
        {
          "name": "height",
          "type": "INT",
          "links": [
            167
          ]
        },
        {
          "name": "length",
          "type": "INT",
          "links": [
            168
          ]
        }
      ],
      "properties": {
        "Node name for S&R": "WanCameraEmbedding",
        "cnr_id": "comfy-core",
        "ver": "0.3.50",
        "enableTabs": false,
        "tabWidth": 65,
        "tabXOffset": 10,
        "hasSecondTab": false,
        "secondTabText": "Send Back",
        "secondTabOffset": 80,
        "secondTabWidth": 65,
        "ue_properties": {
          "widget_ue_connectable": {}
        }
      },
      "widgets_values": [
        "Zoom In",
        832,
        448,
        93,
        0.2,
        0.5,
        0.5,
        0.5,
        0.5
      ]
    },
    {
      "id": 73,
      "type": "SaveVideo",
      "pos": [
        1330,
        1770
      ],
      "size": [
        1080,
        1400
      ],
      "flags": {},
      "order": 20,
      "mode": 0,
      "inputs": [
        {
          "name": "video",
          "type": "VIDEO",
          "link": 153
        }
      ],
      "outputs": [],
      "properties": {
        "Node name for S&R": "SaveVideo",
        "cnr_id": "comfy-core",
        "ver": "0.3.50",
        "enableTabs": false,
        "tabWidth": 65,
        "tabXOffset": 10,
        "hasSecondTab": false,
        "secondTabText": "Send Back",
        "secondTabOffset": 80,
        "secondTabWidth": 65,
        "ue_properties": {
          "widget_ue_connectable": {
            "filename_prefix": true,
            "format": true,
            "codec": true
          }
        }
      },
      "widgets_values": [
        "video/ComfyUI",
        "auto",
        "auto"
      ]
    },
    {
      "id": 81,
      "type": "CLIPTextEncode",
      "pos": [
        250,
        2100
      ],
      "size": [
        600,
        250
      ],
      "flags": {},
      "order": 12,
      "mode": 0,
      "inputs": [
        {
          "name": "clip",
          "type": "CLIP",
          "link": 169
        }
      ],
      "outputs": [
        {
          "name": "CONDITIONING",
          "type": "CONDITIONING",
          "slot_index": 0,
          "links": [
            161
          ]
        }
      ],
      "title": "CLIP Text Encode (Positive Prompt)",
      "properties": {
        "Node name for S&R": "CLIPTextEncode",
        "cnr_id": "comfy-core",
        "ver": "0.3.50",
        "enableTabs": false,
        "tabWidth": 65,
        "tabXOffset": 10,
        "hasSecondTab": false,
        "secondTabText": "Send Back",
        "secondTabOffset": 80,
        "secondTabWidth": 65,
        "ue_properties": {
          "widget_ue_connectable": {}
        }
      },
      "widgets_values": [
        "cinematic static objects, smooth camera movement, atmospheric lighting, detailed environment, film grain, professional cinematography, subtle depth of field, ambient lighting, gradual zoom transition, immersive scene, high quality footage, natural movement, environmental storytelling, cinematic composition, smooth motion blur"
      ],
      "color": "#232",
      "bgcolor": "#353"
    },
    {
      "id": 115,
      "type": "Note",
      "pos": [
        -290,
        1530
      ],
      "size": [
        360,
        100
      ],
      "flags": {},
      "order": 8,
      "mode": 0,
      "inputs": [],
      "outputs": [],
      "title": "About 4 Steps LoRA",
      "properties": {},
      "widgets_values": [
        "Using the Wan2.2 Lighting LoRA will result in the loss of video dynamics, but it will reduce the generation time. This template provides two workflows, and you can enable one as needed."
      ],
      "color": "#432",
      "bgcolor": "#653"
    }
  ],
  "links": [
    [
      149,
      76,
      0,
      71,
      0,
      "MODEL"
    ],
    [
      150,
      80,
      0,
      71,
      1,
      "CONDITIONING"
    ],
    [
      151,
      80,
      1,
      71,
      2,
      "CONDITIONING"
    ],
    [
      152,
      80,
      2,
      71,
      3,
      "LATENT"
    ],
    [
      153,
      83,
      0,
      73,
      0,
      "VIDEO"
    ],
    [
      154,
      85,
      0,
      74,
      0,
      "CLIP"
    ],
    [
      157,
      77,
      0,
      78,
      0,
      "MODEL"
    ],
    [
      158,
      80,
      0,
      78,
      1,
      "CONDITIONING"
    ],
    [
      159,
      80,
      1,
      78,
      2,
      "CONDITIONING"
    ],
    [
      160,
      71,
      0,
      78,
      3,
      "LATENT"
    ],
    [
      161,
      81,
      0,
      80,
      0,
      "CONDITIONING"
    ],
    [
      162,
      74,
      0,
      80,
      1,
      "CONDITIONING"
    ],
    [
      163,
      86,
      0,
      80,
      2,
      "VAE"
    ],
    [
      164,
      79,
      0,
      80,
      4,
      "IMAGE"
    ],
    [
      165,
      87,
      0,
      80,
      5,
      "WAN_CAMERA_EMBEDDING"
    ],
    [
      166,
      87,
      1,
      80,
      6,
      "INT"
    ],
    [
      167,
      87,
      2,
      80,
      7,
      "INT"
    ],
    [
      168,
      87,
      3,
      80,
      8,
      "INT"
    ],
    [
      169,
      85,
      0,
      81,
      0,
      "CLIP"
    ],
    [
      170,
      78,
      0,
      82,
      0,
      "LATENT"
    ],
    [
      171,
      86,
      0,
      82,
      1,
      "VAE"
    ],
    [
      172,
      82,
      0,
      83,
      0,
      "IMAGE"
    ],
    [
      173,
      75,
      0,
      88,
      0,
      "MODEL"
    ],
    [
      174,
      88,
      0,
      76,
      0,
      "MODEL"
    ],
    [
      176,
      90,
      0,
      77,
      0,
      "MODEL"
    ],
    [
      177,
      72,
      0,
      90,
      0,
      "MODEL"
    ]
  ],
  "groups": [
    {
      "id": 1,
      "title": "High noise (first steps)",
      "bounding": [
        -270,
        1730,
        470,
        290
      ],
      "color": "#3f789e",
      "font_size": 24,
      "flags": {}
    },
    {
      "id": 2,
      "title": "Step 3 - Prompt",
      "bounding": [
        230,
        2030,
        640,
        600
      ],
      "color": "#3f789e",
      "font_size": 24,
      "flags": {}
    },
    {
      "id": 5,
      "title": "Step 1 - Load models",
      "bounding": [
        -280,
        1690,
        490,
        940
      ],
      "color": "#3f789e",
      "font_size": 24,
      "flags": {}
    },
    {
      "id": 3,
      "title": "Low noise (last steps)",
      "bounding": [
        -270,
        2040,
        470,
        310
      ],
      "color": "#3f789e",
      "font_size": 24,
      "flags": {}
    },
    {
      "id": 6,
      "title": "Step 2 - Upload start_image",
      "bounding": [
        -280,
        2650,
        490,
        570
      ],
      "color": "#3f789e",
      "font_size": 24,
      "flags": {}
    },
    {
      "id": 7,
      "title": "Step 4 - Camera Conditions",
      "bounding": [
        230,
        2650,
        640,
        570
      ],
      "color": "#3f789e",
      "font_size": 24,
      "flags": {}
    },
    {
      "id": 14,
      "title": "Wan2.2 Fun Camera fp8 scaled + LightX2V 4 Steps LoRA",
      "bounding": [
        -290,
        1650,
        2700,
        1580
      ],
      "color": "#3f789e",
      "font_size": 24,
      "flags": {}
    }
  ],
  "config": {},
  "extra": {
    "ds": {
      "scale": 0.7156787015770216,
      "offset": [
        938.0883143828347,
        -2459.2858156034486
      ]
    },
    "frontendVersion": "1.25.9",
    "ue_links": [],
    "links_added_by_ue": [],
    "VHS_latentpreview": false,
    "VHS_latentpreviewrate": 0,
    "VHS_MetadataImage": true,
    "VHS_KeepIntermediate": true
  },
  "version": 0.4
}